simple_sql/__init__.py
simple_sql/database.py
simple_sql/exceptions.py
simple_sql/metadata.py
simple_sql/model/__init__.py
simple_sql/model/column.py
simple_sql/model/foreign_key.py
simple_sql/model/table.py
simple_sql/model/type.py
simple_sql/model/types_enum.py
simple_sql/statements/__init__.py
simple_sql/statements/delete.py
simple_sql/statements/drop_table.py
simple_sql/statements/insert_into.py
simple_sql/statements/select.py
simple_sql/statements/update.py
simple_sql/wrappers/__init__.py
simple_sql/wrappers/delete_wrapper.py
simple_sql/wrappers/drop_table_wrapper.py
simple_sql/wrappers/insert_into_wrapper.py
simple_sql/wrappers/select_wrapper.py
simple_sql/wrappers/update_wrapper.py
simple_sql_riccardoob-1.0.0.dist-info/LICENSE
simple_sql_riccardoob-1.0.0.dist-info/METADATA
simple_sql_riccardoob-1.0.0.dist-info/WHEEL
simple_sql_riccardoob-1.0.0.dist-info/top_level.txt
simple_sql_riccardoob-1.0.0.dist-info/RECORD
