Metadata-Version: 2.1
Name: simple-sql-riccardoob
Version: 1.0.0
Summary: Simple MySQL ORM
Home-page: https://github.com/RiccardoBarbieri/simple_sql
Author: Riccardo Barbieri
Author-email: riccardo_barbieri@outlook.it
License: UNKNOWN
Project-URL: Bug Tracker, https://github.com/RiccardoBarbieri/simple_sql/issues
Platform: UNKNOWN
Classifier: Programming Language :: Python :: 3
Classifier: License :: OSI Approved :: MIT License
Classifier: Operating System :: OS Independent
Requires-Python: >=3.6
